azuredatacollector/__init__.py
azuredatacollector/datacollector.py
azuredatacollector/datacollector_test.py
azure_data_collector-0.1.5.dist-info/LICENSE.txt
azure_data_collector-0.1.5.dist-info/METADATA
azure_data_collector-0.1.5.dist-info/WHEEL
azure_data_collector-0.1.5.dist-info/top_level.txt
azure_data_collector-0.1.5.dist-info/RECORD
