Metadata-Version: 2.1
Name: azure-data-collector
Version: 0.1.5
Summary: Azure Monitor Data Collector API Client
Home-page: https://github.com/aka0/azure-data-collector
Author: Arthur Kao
Author-email: aka0@outlook.com
License: MIT
Classifier: License :: OSI Approved :: MIT License
Classifier: Programming Language :: Python
Classifier: Programming Language :: Python :: 3
Classifier: Programming Language :: Python :: 3.6
Classifier: Programming Language :: Python :: Implementation :: CPython
Classifier: Programming Language :: Python :: Implementation :: PyPy
Requires-Python: >=3.9.0
License-File: LICENSE.txt
Requires-Dist: requests
